dynamic_executor/__init__.py
dynamic_executor/classes/DynamicClassCreator.py
dynamic_executor/classes/DynamicClassModule.py
dynamic_executor/classes/__init__.py
dynamic_executor/utils/DynamicModeExecutor.py
dynamic_executor/utils/__init__.py
dynamic_executor/utils/_get_dynamic_classes.py
dynamic_executor/utils/_get_modules.py
dynamic_executor/utils/_re_import.py
dynamic_executor-1.2.6.dist-info/LICENSE
dynamic_executor-1.2.6.dist-info/METADATA
dynamic_executor-1.2.6.dist-info/WHEEL
dynamic_executor-1.2.6.dist-info/top_level.txt
dynamic_executor-1.2.6.dist-info/RECORD
