Metadata-Version: 2.1
Name: dynamic-executor
Version: 1.2.6
Summary: Module for making changes in code during runtime
Home-page: https://github.com/Tesla2000/dython
Author: Tesla2000
Author-email: fratajczak124@gmail.com
Project-URL: Homepage, https://github.com/Tesla2000/dython
Classifier: Programming Language :: Python :: 3
Classifier: License :: OSI Approved :: MIT License
Classifier: Operating System :: OS Independent
Requires-Python: >=3.5
License-File: LICENSE
